{
  "db_name": "PostgreSQL",
  "query": "SELECT * FROM items ORDER BY name LIMIT $1 OFFSET $2",
  "describe": {
    "columns": [
      {
        "ordinal": 0,
        "name": "uuid",
        "type_info": "Uuid"
      },
      {
        "ordinal": 1,
        "name": "created_at",
        "type_info": "Timestamptz"
      },
      {
        "ordinal": 2,
        "name": "updated_at",
        "type_info": "Timestamptz"
      },
      {
        "ordinal": 3,
        "name": "name",
        "type_info": "Text"
      },
      {
        "ordinal": 4,
        "name": "price",
        "type_info": "Numeric"
      }
    ],
    "parameters": {
      "Left": [
        "Int8",
        "Int8"
      ]
    },
    "nullable": [
      false,
      false,
      false,
      false,
      false
    ]
  },
  "hash": "66468e2f0902badc5a6ef864c94a9069bfc21bac80be355b8e461c2fc6fd0fce"
}
